unraid_api/__init__.py
unraid_api/async_client.py
unraid_api/auth.py
unraid_api/client.py
unraid_api/client_async.py
unraid_api/exceptions.py
unraid_api/subscription.py
unraid_api/cli/__init__.py
unraid_api/cli/client.py
unraid_api/models/__init__.py
unraid_api/models/array.py
unraid_api/models/config.py
unraid_api/models/disk.py
unraid_api/models/docker.py
unraid_api/models/info.py
unraid_api/models/notification.py
unraid_api/models/user.py
unraid_api/models/vm.py
unraid_api/resources/__init__.py
unraid_api/resources/array.py
unraid_api/resources/config.py
unraid_api/resources/disk.py
unraid_api/resources/docker.py
unraid_api/resources/info.py
unraid_api/resources/notification.py
unraid_api/resources/user.py
unraid_api/resources/vm.py
unraid_api-1.0.0.dist-info/licenses/LICENSE
unraid_api-1.0.0.dist-info/METADATA
unraid_api-1.0.0.dist-info/WHEEL
unraid_api-1.0.0.dist-info/entry_points.txt
unraid_api-1.0.0.dist-info/top_level.txt
unraid_api-1.0.0.dist-info/RECORD
