Metadata-Version: 2.4
Name: unraid-api
Version: 1.0.0
Summary: Python library for controlling and monitoring Unraid servers via GraphQL API
Home-page: https://github.com/domalab/unraid-api
Author: Ruaan Deysel
Author-email: ruaan.deysel@gmail.com
Project-URL: Documentation, https://github.com/domalab/unraid-api
Project-URL: Source, https://github.com/domalab/unraid-api
Project-URL: Bug Tracker, https://github.com/domalab/unraid-api/issues
Keywords: unraid,api,graphql,home-assistant,automation,nas
Classifier: Development Status :: 5 - Production/Stable
Classifier: Intended Audience :: Developers
Classifier: License :: OSI Approved :: MIT License
Classifier: Programming Language :: Python :: 3
Classifier: Programming Language :: Python :: 3.9
Classifier: Programming Language :: Python :: 3.10
Classifier: Programming Language :: Python :: 3.11
Requires-Python: >=3.9
License-File: LICENSE
Requires-Dist: httpx>=0.23.0
Requires-Dist: pydantic>=2.0.0
Requires-Dist: graphql-core>=3.2.0
Requires-Dist: typeguard>=2.13.0
Requires-Dist: websockets>=10.3
Requires-Dist: rich>=12.0.0
Provides-Extra: dev
Requires-Dist: pytest>=7.0.0; extra == "dev"
Requires-Dist: pytest-asyncio>=0.18.0; extra == "dev"
Requires-Dist: pytest-cov>=3.0.0; extra == "dev"
Requires-Dist: black>=23.0.0; extra == "dev"
Requires-Dist: isort>=5.10.0; extra == "dev"
Requires-Dist: mypy>=0.950; extra == "dev"
Dynamic: author
Dynamic: author-email
Dynamic: classifier
Dynamic: description
Dynamic: description-content-type
Dynamic: home-page
Dynamic: keywords
Dynamic: license-file
Dynamic: project-url
Dynamic: provides-extra
Dynamic: requires-dist
Dynamic: requires-python
Dynamic: summary
